setup.py
bidistributions_probability/Binomialdistribution.py
bidistributions_probability/Gaussiandistribution.py
bidistributions_probability/Generaldistribution.py
bidistributions_probability/__init__.py
bidistributions_probablity.egg-info/PKG-INFO
bidistributions_probablity.egg-info/SOURCES.txt
bidistributions_probablity.egg-info/dependency_links.txt
bidistributions_probablity.egg-info/not-zip-safe
bidistributions_probablity.egg-info/top_level.txt