Metadata-Version: 1.0
Name: bidistributions-probablity
Version: 0.1
Summary: Gaussian distributions
Home-page: UNKNOWN
Author: Jayanth Adithya
Author-email: njayanthaithya@gmail.com
License: UNKNOWN
Platform: UNKNOWN
